buildpeople/__init__.py
buildpeople/main.py
buildpeople-0.1.1.dist-info/METADATA
buildpeople-0.1.1.dist-info/WHEEL
buildpeople-0.1.1.dist-info/entry_points.txt
buildpeople-0.1.1.dist-info/top_level.txt
buildpeople-0.1.1.dist-info/RECORD
